SMUTHI.libs/libgfortran-040039e1.so.5.0.0
SMUTHI.libs/libgomp-a34b3233.so.1.0.0
SMUTHI.libs/libquadmath-96973f99.so.0.0.0
smuthi/__init__.py
smuthi/initial_field.py
smuthi/layers.py
smuthi/particles.py
smuthi/simulation.py
smuthi/version.py
smuthi/fields/__init__.py
smuthi/fields/expansions.py
smuthi/fields/expansions_cuda.py
smuthi/fields/spherical_harmonic_translations.py
smuthi/fields/transformations.py
smuthi/fields/vector_wave_functions.py
smuthi/linearsystem/__init__.py
smuthi/linearsystem/linear_system.py
smuthi/linearsystem/linear_system_cuda.py
smuthi/linearsystem/particlecoupling/__init__.py
smuthi/linearsystem/particlecoupling/direct_coupling.py
smuthi/linearsystem/particlecoupling/layer_mediated_coupling.py
smuthi/linearsystem/particlecoupling/prepare_lookup.py
smuthi/linearsystem/particlecoupling/prepare_lookup_cuda.py
smuthi/linearsystem/tmatrix/__init__.py
smuthi/linearsystem/tmatrix/t_matrix.py
smuthi/linearsystem/tmatrix/nfmds/__init__.py
smuthi/linearsystem/tmatrix/nfmds/indexconverter.py
smuthi/linearsystem/tmatrix/nfmds/nfmds.cpython-39-x86_64-linux-gnu.so
smuthi/linearsystem/tmatrix/nfmds/stlmanager.py
smuthi/linearsystem/tmatrix/nfmds/NFM-DS/_README.txt
smuthi/linearsystem/tmatrix/nfmds/NFM-DS/INPUTFILES/Input.dat
smuthi/linearsystem/tmatrix/nfmds/NFM-DS/INPUTFILES/InputAXSYM.dat
smuthi/linearsystem/tmatrix/nfmds/NFM-DS/INPUTFILES/InputCOMP.dat
smuthi/linearsystem/tmatrix/nfmds/NFM-DS/INPUTFILES/InputEFMED.dat
smuthi/linearsystem/tmatrix/nfmds/NFM-DS/INPUTFILES/InputINHOM.dat
smuthi/linearsystem/tmatrix/nfmds/NFM-DS/INPUTFILES/InputINHOM2SPH.dat
smuthi/linearsystem/tmatrix/nfmds/NFM-DS/INPUTFILES/InputINHOMSPH.dat
smuthi/linearsystem/tmatrix/nfmds/NFM-DS/INPUTFILES/InputINHOMSPHREC.dat
smuthi/linearsystem/tmatrix/nfmds/NFM-DS/INPUTFILES/InputLAY.dat
smuthi/linearsystem/tmatrix/nfmds/NFM-DS/INPUTFILES/InputMULT.dat
smuthi/linearsystem/tmatrix/nfmds/NFM-DS/INPUTFILES/InputMULT2SPH.dat
SMUTHI-2.2.4.dist-info/METADATA
SMUTHI-2.2.4.dist-info/WHEEL
SMUTHI-2.2.4.dist-info/top_level.txt
SMUTHI-2.2.4.dist-info/RECORD
