Metadata-Version: 2.1
Name: SMUTHI
Version: 2.2.4
Summary: Light scattering by multiple particles in thin-film systems
Home-page: https://gitlab.com/AmosEgel/smuthi
Author: Amos Egel
Author-email: amos.egel@gmail.com
License: MIT
Platform: UNKNOWN
Requires-Dist: numpy<2.0,>=1.19.3
Requires-Dist: argparse
Requires-Dist: imageio
Requires-Dist: matplotlib
Requires-Dist: mpmath
Requires-Dist: numba
Requires-Dist: pyyaml
Requires-Dist: scipy<1.14
Requires-Dist: sympy
Requires-Dist: tqdm
Requires-Dist: h5py
Requires-Dist: pycparser
Requires-Dist: psutil
Requires-Dist: pywigxjpf
Provides-Extra: cuda
Requires-Dist: PyCuda; extra == "cuda"
